{
    "mods": [
        {
            "name": "Dark-MoreHardStorms",
            "author": "DarkAngel",
            "version": "3.0",
            "compatibility": "All",
            "description": "An immersive weather overhaul that reshapes Icarus' climate. Storms are more frequent, last longer, and strike harder, creating a hostile and unpredictable world where timing, shelter, and preparation matter more than ever.",
            "imageURL": "",
            "readmeURL": "https://github.com/DarkEsteves/IcarusMods/raw/main/README.md",
            "files": {
                "exmodz": "https://github.com/DarkEsteves/IcarusMods/raw/main/Dark-MoreHardStorms.EXMODZ"
            }
        },
        {
            "name": "Dark-UndersuitsPlus",
            "author": "DarkAngel",
            "version": "1.1",
            "compatibility": "All",
            "description": "Dark-UndersuitsPlus enhances existing undersuits with improved stats and better balance, making them more useful throughout progression without breaking immersion, compatibility and original identity.",
            "imageURL": "",
            "readmeURL": "https://github.com/DarkEsteves/IcarusMods/raw/main/README.md",
            "files": {
                "exmodz": "https://github.com/DarkEsteves/IcarusMods/raw/main/Dark-UndersuitsPlus.EXMODZ"
            }
        },
        {
            "name": "Dark-ElectricFabricator",
            "author": "DarkAngel",
            "version": "3.0",
            "compatibility": "All",
            "description": "Make the Fabricator need energy to work, as it should be from beginning, now the fabricator needs 2500 energy to work. And in adition have moved the Portable Biofuel Generator and Spline Tool Electricity to Tier 3, and added the Jimk72 Windmill Generator 1.4.",
            "imageURL": "",
            "readmeURL": "https://github.com/DarkEsteves/IcarusMods/raw/main/README.md",
            "files": {
                "exmodz": "https://github.com/DarkEsteves/IcarusMods/raw/main/Dark-ElectricFabricator.EXMODZ"
            }
        },
        {
            "name": "Dark-Workshop",
            "author": "DarkAngel",
            "version": "2.0",
            "compatibility": "All",
            "description": "Workshop tab with Armour, modules and some other goodies ..",
            "imageURL": "https://github.com/DarkEsteves/IcarusMods/raw/main/DarkMods.png",
            "readmeURL": "https://github.com/DarkEsteves/IcarusMods/raw/main/README.md",
            "files": {
                "exmodz": "https://github.com/DarkEsteves/IcarusMods/raw/main/Dark-Workshop.EXMODZ"
            }
        },
        {
            "name": "Dark-NewMetaExtractionTweaks",
            "author": "DarkAngel",
            "version": "1.0",
            "compatibility": "All",
            "description": "This mod rebalances and enhances the Meta-tier extraction equipment by improving power management, battery capacity, and crafting costs, making late-game devices more efficient and practical to use. Reduced battery capacity to 25000, crafting costs are rebalanced, the radar now needs meta power source, but the battery is now chargeable in the charging device that can now have 2 slots to charge and the extractor have 2 slots too to add batteries.",
            "imageURL": "https://github.com/DarkEsteves/IcarusMods/raw/main/DarkMods.png",
            "readmeURL": "https://github.com/DarkEsteves/IcarusMods/raw/main/README.md",
            "files": {
                "exmodz": "https://github.com/DarkEsteves/IcarusMods/raw/main/Dark-NewMetaExtractionTweaks.EXMODZ"
            }
        },
        {
            "name": "Dark-Bags",
            "author": "DarkAngel",
            "version": "1.1",
            "compatibility": "All",
            "description": "Adds three specialized bags to Icarus: a Big Bag for heavy cargo, a Food Bag to keep your provisions fresh, and an Ammo Bag for all your ammunition needs.",
            "imageURL": "https://github.com/DarkEsteves/IcarusMods/raw/main/DarkMods.png",
            "readmeURL": "https://github.com/DarkEsteves/IcarusMods/raw/main/README.md",
            "files": {
                "exmodz": "https://github.com/DarkEsteves/IcarusMods/raw/main/Dark-Bags.EXMODZ"
            }
        },
        {
            "name": "Dark-Bags",
            "author": "DarkAngel",
            "version": "1.1",
            "compatibility": "All",
            "description": "Adds three specialized bags to Icarus: a Big Bag for heavy cargo, a Food Bag to keep your provisions fresh, and an Ammo Bag for all your ammunition needs.",
            "imageURL": "https://github.com/DarkEsteves/IcarusMods/raw/main/DarkMods.png",
            "readmeURL": "https://github.com/DarkEsteves/IcarusMods/raw/main/README.md",
            "files": {
                "exmodz": "https://github.com/DarkEsteves/IcarusMods/raw/main/Dark-Bags.EXMODZ"
            }
        },
        {
            "name": "Dark-Shops",
            "author": "DarkAngel",
            "version": "1.0",
            "compatibility": "All",
            "description": "Rebalanced shop prices and trade quantities across all exchanges — because your work as a prospector deserves fair value.",
            "imageURL": "https://github.com/DarkEsteves/IcarusMods/raw/main/DarkMods.png",
            "readmeURL": "https://github.com/DarkEsteves/IcarusMods/raw/main/README.md",
            "files": {
                "exmodz": "https://github.com/DarkEsteves/IcarusMods/raw/main/Dark-Shops.EXMODZ"
            }
        }
    ]
}





















